gglasso/__init__.py
gglasso/problem.py
gglasso/helper/__init__.py
gglasso/helper/basic_linalg.py
gglasso/helper/data_generation.py
gglasso/helper/experiment_helper.py
gglasso/helper/ext_admm_helper.py
gglasso/helper/model_selection.py
gglasso/helper/utils.py
gglasso/solver/__init__.py
gglasso/solver/admm_solver.py
gglasso/solver/ext_admm_solver.py
gglasso/solver/fgl_helper.py
gglasso/solver/functional_sgl_admm.py
gglasso/solver/ggl_helper.py
gglasso/solver/ppdna_solver.py
gglasso/solver/single_admm_solver.py
gglasso/solver/old/ppdna_unjitted.py
gglasso-0.2.1.dist-info/METADATA
gglasso-0.2.1.dist-info/WHEEL
gglasso-0.2.1.dist-info/licenses/LICENSE.txt
gglasso-0.2.1.dist-info/RECORD
