Metadata-Version: 2.4
Name: gglasso
Version: 0.2.1
Summary: Algorithms for Single and Multiple Graphical Lasso problems.
Project-URL: Documentation, https://gglasso.readthedocs.io/en/stable/
Project-URL: Issues, https://github.com/fabian-sp/GGLasso/issues
Project-URL: Source, https://github.com/fabian-sp/GGLasso
Author: Oleg Vlasovets, Christian L. Müller
Author-email: Fabian Schaipp <fabian.schaipp@tum.de>
License-Expression: MIT
License-File: LICENSE.txt
Keywords: graphcial models,graphical lasso,network inference,optimization
Classifier: Development Status :: 5 - Production/Stable
Classifier: License :: OSI Approved :: MIT License
Classifier: Programming Language :: Python
Classifier: Programming Language :: Python :: 3.9
Classifier: Programming Language :: Python :: 3.10
Classifier: Programming Language :: Python :: 3.11
Classifier: Programming Language :: Python :: 3.12
Classifier: Programming Language :: Python :: Implementation :: CPython
Classifier: Programming Language :: Python :: Implementation :: PyPy
Requires-Python: >=3.9
Requires-Dist: matplotlib
Requires-Dist: networkx
Requires-Dist: numba<0.60.0,>=0.46.0
Requires-Dist: numpy<2.0.0,>=1.17.3
Requires-Dist: pandas
Requires-Dist: scikit-learn>=0.24.1
Requires-Dist: scipy>=0.11.0
Requires-Dist: seaborn
Provides-Extra: docs
Requires-Dist: sphinx; extra == 'docs'
Requires-Dist: sphinx-gallery; extra == 'docs'
Requires-Dist: sphinx-rtd-theme; extra == 'docs'
Provides-Extra: examples
Requires-Dist: regain; extra == 'examples'
Requires-Dist: scikit-fda; extra == 'examples'
Provides-Extra: tests
Requires-Dist: pytest; extra == 'tests'
Requires-Dist: pytest-cov; extra == 'tests'
